{"name":"Mang Theo Không Gian Cả Nhà Xuyên Cổ Chạy Nạn","folder":"mangtheokhonggiancanhaxuyencochaynan","tacGia":"Nhất Chu Nhất Phạn","theLoai":"Ngôn Tình","trangThai":"Đang ra","description":"Tác giả: Nhất Chu Nhất Phạn<br><br>Thể loại: Dị Năng, Truyện Nữ Cường, Cổ Đại, Hài Hước, Điền Văn, Ngôn Tình, Truyện Khác, Xuyên Không, Truyện Gia Đấu, Thám Hiểm, Huyền huyễn<br><br>Giới thiệu:<br><br>Quý Tinh Nhiên hoàn toàn không ngờ, chỉ đi leo núi một chuyến mà một nhà ba người liền xuyên qua.<br><br>Đã vậy bọn họ còn xuyên đến đội ngũ bị lưu đày, phải tới nơi lạnh giá khổ cực.<br><br>May mắn thay, ba lô của họ là một không gian, Quý Tinh Nhiên còn có kỹ năng sinh tồn đặc biệt, có thể dự đoán thời tiết, thu thập trái cây dại và trao đổi vật tư…<br><br>Cha Quý thân là một ông chủ của công ty xây dựng, thét to để chỉ người cổ đại xây dựng các công trình trên chống cháy chống sét, dưới thì chống mưa lũ.<br><br>Trong khi mẹ Quý ở bên cạnh phổ cập kiến thức y học, vừa nói còn vừa đan giày rơm.<br><br>Cả gia đình cùng đồng tâm hiệp lực, dẫn dắt cả tộc nhân lưu đày sống một cuộc sống hạnh phúc trên con đường thoát khỏi nạn đói!"}